odoo/addons/stock_barcodes/README.rst
odoo/addons/stock_barcodes/__init__.py
odoo/addons/stock_barcodes/__manifest__.py
odoo/addons/stock_barcodes/hooks.py
odoo/addons/stock_barcodes/data/stock_barcodes_action.xml
odoo/addons/stock_barcodes/data/stock_barcodes_option.xml
odoo/addons/stock_barcodes/i18n/es.po
odoo/addons/stock_barcodes/i18n/fr.po
odoo/addons/stock_barcodes/i18n/it.po
odoo/addons/stock_barcodes/i18n/stock_barcodes.pot
odoo/addons/stock_barcodes/i18n/tr.po
odoo/addons/stock_barcodes/models/__init__.py
odoo/addons/stock_barcodes/models/barcode_events_mixin.py
odoo/addons/stock_barcodes/models/stock_barcodes_action.py
odoo/addons/stock_barcodes/models/stock_barcodes_option.py
odoo/addons/stock_barcodes/models/stock_move.py
odoo/addons/stock_barcodes/models/stock_move_line.py
odoo/addons/stock_barcodes/models/stock_picking.py
odoo/addons/stock_barcodes/models/stock_picking_type.py
odoo/addons/stock_barcodes/models/stock_quant.py
odoo/addons/stock_barcodes/readme/CONTRIBUTORS.rst
odoo/addons/stock_barcodes/readme/DESCRIPTION.rst
odoo/addons/stock_barcodes/readme/HISTORY.rst
odoo/addons/stock_barcodes/readme/ROADMAP.rst
odoo/addons/stock_barcodes/readme/USAGE.rst
odoo/addons/stock_barcodes/reports/__init__.py
odoo/addons/stock_barcodes/reports/barcode_actions_report.py
odoo/addons/stock_barcodes/reports/barcode_actions_report.xml
odoo/addons/stock_barcodes/reports/reports.xml
odoo/addons/stock_barcodes/security/ir.model.access.csv
odoo/addons/stock_barcodes/static/description/icon.png
odoo/addons/stock_barcodes/static/description/icon.svg
odoo/addons/stock_barcodes/static/description/index.html
odoo/addons/stock_barcodes/static/src/docs/barcodes_actions.pdf
odoo/addons/stock_barcodes/static/src/docs/barcodes_demo.pdf
odoo/addons/stock_barcodes/static/src/img/add_product.png
odoo/addons/stock_barcodes/static/src/img/apply_inventory.png
odoo/addons/stock_barcodes/static/src/img/apply_inventory_reason.png
odoo_addon_stock_barcodes-16.0.2.2.1.dist-info/METADATA
odoo_addon_stock_barcodes-16.0.2.2.1.dist-info/WHEEL
odoo_addon_stock_barcodes-16.0.2.2.1.dist-info/top_level.txt
odoo_addon_stock_barcodes-16.0.2.2.1.dist-info/RECORD
