Metadata-Version: 2.1
Name: odoo-addon-stock_barcodes
Version: 16.0.2.2.1
Summary: It provides read barcode on stock operations.
Home-page: https://github.com/OCA/stock-logistics-barcode
Author: Tecnativa, Odoo Community Association (OCA)
Author-email: support@odoo-community.org
License: AGPL-3
Classifier: Programming Language :: Python
Classifier: Framework :: Odoo
Classifier: Framework :: Odoo :: 16.0
Classifier: License :: OSI Approved :: GNU Affero General Public License v3
Requires-Python: >=3.10
Requires-Dist: odoo-addon-web-widget-numeric-step<16.1dev,>=16.0dev
Requires-Dist: odoo<16.1dev,>=16.0a
